azapyGUI/AppSettingsPage.py
azapyGUI/AppSettingsPageMisc.py
azapyGUI/AppSettingsWindow.py
azapyGUI/BacktestComputation.py
azapyGUI/BacktestEntryWindow.py
azapyGUI/BacktestMenuPortfolioWindow.py
azapyGUI/CloneMenuPortfolioWindow.py
azapyGUI/CrossHairBCursor.py
azapyGUI/DF_Window.py
azapyGUI/DF_table.py
azapyGUI/EditMenuPortfolioWindow.py
azapyGUI/EditPortfolioWindow.py
azapyGUI/EntryClonePortfolioWindow.py
azapyGUI/EntryNameWindow.py
azapyGUI/EntryRenamePortfolioWindow.py
azapyGUI/GetMktData.py
azapyGUI/MenuApp.py
azapyGUI/MktDataFrame.py
azapyGUI/MktDataNode.py
azapyGUI/ModelParamEditWindow.py
azapyGUI/NrShares_table.py
azapyGUI/PortAnalyseWindow.py
azapyGUI/PortDataNode.py
azapyGUI/PortfolioFrame.py
azapyGUI/RebalanceMenuPortfolioWindow.py
azapyGUI/RemoveMenuPortfolioWindow.py
azapyGUI/SaveMenuPortfolioWindow.py
azapyGUI/Scrollable.py
azapyGUI/SelectOneWindow.py
azapyGUI/SymbAnalyseWindow.py
azapyGUI/SymbExtractWindow.py
azapyGUI/SymbTableEntry.py
azapyGUI/TimeSeriesViewWindow.py
azapyGUI/ViewTip.py
azapyGUI/ViewTip_Ubuntu.py
azapyGUI/ViewTip_fade.py
azapyGUI/ViewTip_fast.py
azapyGUI/WeightsWindow.py
azapyGUI/__init__.py
azapyGUI/azHelper.py
azapyGUI/azapyApp.py
azapyGUI/config.py
azapyGUI/configHelps.py
azapyGUI/configMSG.py
azapyGUI/configModels.py
azapyGUI/configPlot.py
azapyGUI/configSettings.py
azapyGUI/configTips.py
azapyGUI/mktDataValidation.py
azapyGUI/modelParametersValidation.py
azapyGUI/serviceMasterUserConfig.py
azapyGUI/tkHelper.py
azapyGUI-0.1.1.dist-info/LICENSE
azapyGUI-0.1.1.dist-info/METADATA
azapyGUI-0.1.1.dist-info/WHEEL
azapyGUI-0.1.1.dist-info/top_level.txt
azapyGUI-0.1.1.dist-info/RECORD
