Metadata-Version: 2.1
Name: azapyGUI
Version: 0.1.1
Summary: GUI for azapy library - Financial Portfolio Optimization Algorithms
Home-page: https://github.com/Mircea-MMXXI/azapyGUI.git
Author: Mircea Marinescu
Author-email: mircea.marinescu@outlook.com
License: GPLv3
Project-URL: Documentation, https://azapyGUI.readthedocs.io/en/latest
Project-URL: Source, https://github.com/Mircea-MMXXI/azapyGUI
Project-URL: Bug Tracker, https://github.com/Mircea-MMXXI/azapyGUI/issues
Classifier: Programming Language :: Python :: 3
Classifier: License :: OSI Approved :: GNU General Public License v3 (GPLv3)
Classifier: Operating System :: OS Independent
Requires-Python: >=3.11
License-File: LICENSE
Requires-Dist: azapy >=1.2.5
Requires-Dist: numpy
Requires-Dist: pandas
Requires-Dist: matplotlib
Requires-Dist: xlsxwriter ; platform_system == "Windows"
